pieroutine/__init__.py
pieroutine/process.py
pieroutine/wait_group.py
pieroutine-0.2.2.dist-info/METADATA
pieroutine-0.2.2.dist-info/WHEEL
pieroutine-0.2.2.dist-info/RECORD
