Metadata-Version: 2.4
Name: pieroutine
Version: 0.2.2
Summary: 
Author: AmirRedHat
Author-email: amir.ch.charehei1382@gmail.com
Requires-Python: >=3.12
Classifier: Programming Language :: Python :: 3
Classifier: Programming Language :: Python :: 3.12
Classifier: Programming Language :: Python :: 3.13
Classifier: Programming Language :: Python :: 3.14
